koru-utilities/__init__.py
koru-utilities/cloudwatch.py
koru-utilities/mail.py
korutools/__init__.py
korutools/cloudwatch.py
korutools/mail.py
korutools-0.0.2.dist-info/METADATA
korutools-0.0.2.dist-info/WHEEL
korutools-0.0.2.dist-info/top_level.txt
korutools-0.0.2.dist-info/RECORD
