Metadata-Version: 2.1
Name: korutools
Version: 0.0.2
Summary: A package that contains utilities for logging and notifications
Home-page: https://bitbucket.org/rodionlim/koru-utilities/src/master/
Author: Koru Tech
Author-email: tech@koruparnters.com
License: UNKNOWN
Platform: UNKNOWN
Classifier: Programming Language :: Python :: 3
Classifier: License :: OSI Approved :: MIT License
Classifier: Operating System :: OS Independent
Requires-Python: >=3.6
